nonebot_plugin_bertvits2/__init__.py
nonebot_plugin_bertvits2/api.py
nonebot_plugin_bertvits2/config.py
nonebot_plugin_bertvits2/server_fastapi.py
nonebot_plugin_bertvits2-0.1.3.dist-info/METADATA
nonebot_plugin_bertvits2-0.1.3.dist-info/WHEEL
nonebot_plugin_bertvits2-0.1.3.dist-info/RECORD
