Metadata-Version: 2.1
Name: nonebot-plugin-bertvits2
Version: 0.1.3
Summary: 
Author: Sora
Author-email: atri@suzakuintsubaki.com
Requires-Python: >=3.10,<4.0
Classifier: Programming Language :: Python :: 3
Classifier: Programming Language :: Python :: 3.10
Classifier: Programming Language :: Python :: 3.11
Classifier: Programming Language :: Python :: 3.12
Requires-Dist: aiohttp (>=3.8.6,<4.0.0)
Requires-Dist: nonebot-adapter-onebot (>=2.3.1,<3.0.0)
Requires-Dist: nonebot2 (>=2.1.0,<3.0.0)
